_bdew_datetimes_version.py
bdew_datetimes/__init__.py
bdew_datetimes/calendar.py
bdew_datetimes/enums.py
bdew_datetimes/german_strom_and_gas_tag.py
bdew_datetimes/german_time_zone.py
bdew_datetimes/models.py
bdew_datetimes/periods.py
bdew_datetimes/py.typed
bdew_datetimes-0.10.0.dist-info/METADATA
bdew_datetimes-0.10.0.dist-info/WHEEL
bdew_datetimes-0.10.0.dist-info/licenses/LICENSE
bdew_datetimes-0.10.0.dist-info/RECORD
