Metadata-Version: 2.4
Name: bdew_datetimes
Version: 0.10.0
Summary: Generate and work with holidays of the BDEW-Calendar for power and gas in Germany
Project-URL: Changelog, https://github.com/mj0nez/bdew-datetimes/releases
Project-URL: Homepage, https://github.com/mj0nez/bdew-datetimes/
Author: Konstantin Klein
Author-email: Marcel Johannesmann <mj0nez@fn.de>
License: MIT
License-File: LICENSE
Keywords: bdew,edi@energy
Classifier: Development Status :: 4 - Beta
Classifier: Environment :: Console
Classifier: Intended Audience :: Developers
Classifier: License :: OSI Approved :: MIT License
Classifier: Operating System :: OS Independent
Classifier: Programming Language :: Python
Classifier: Programming Language :: Python :: 3 :: Only
Classifier: Programming Language :: Python :: 3.10
Classifier: Programming Language :: Python :: 3.11
Classifier: Programming Language :: Python :: 3.12
Classifier: Programming Language :: Python :: 3.13
Classifier: Programming Language :: Python :: 3.14
Requires-Python: >=3.10
Requires-Dist: holidays>=0.84; python_version >= '3.10'
Requires-Dist: python-dateutil
Requires-Dist: pytz>=2022.7.1
Provides-Extra: formatting
Requires-Dist: black==25.9.0; extra == 'formatting'
Requires-Dist: isort==6.1.0; extra == 'formatting'
Provides-Extra: linting
Requires-Dist: pylint==3.3.9; extra == 'linting'
Provides-Extra: packaging
Requires-Dist: build==1.3.0; extra == 'packaging'
Requires-Dist: twine==6.2.0; extra == 'packaging'
Provides-Extra: spell-check
Requires-Dist: codespell==2.4.1; extra == 'spell-check'
Provides-Extra: tests
Requires-Dist: pytest==8.4.2; extra == 'tests'
Provides-Extra: type-check
Requires-Dist: mypy==1.18.2; extra == 'type-check'
Requires-Dist: types-python-dateutil==2.9.0.20251008; extra == 'type-check'
Requires-Dist: types-pytz==2025.2.0.20250809; extra == 'type-check'
